asammdfplus/__init__.py
asammdfplus/_original.py
asammdfplus/_typing.py
asammdfplus/_utils.py
asammdfplus/io.py
asammdfplus/mda.py
asammdfplus/mdf.py
asammdfplus/setup.py
asammdfplus-8.0.2.dist-info/METADATA
asammdfplus-8.0.2.dist-info/WHEEL
asammdfplus-8.0.2.dist-info/RECORD
