Metadata-Version: 2.1
Name: asammdfplus
Version: 8.0.2
Summary: A wrapper for asammdf with additional features
License: MIT
Author: c0sogi
Author-email: dcas@naver.com
Requires-Python: >=3.10
Classifier: License :: OSI Approved :: MIT License
Classifier: Programming Language :: Python :: 3
Classifier: Programming Language :: Python :: 3.10
Classifier: Programming Language :: Python :: 3.11
Classifier: Programming Language :: Python :: 3.12
Requires-Dist: asammdf (>=8.0.0,<8.1.0)
Requires-Dist: matplotlib (>=3.0.0,<4)
Requires-Dist: numpy (>=1.20.0,<3)
Requires-Dist: pandas (>=1.5.0,<3)
